sqlmodelgen/__init__.py
sqlmodelgen/sqlmodelgen.py
sqlmodelgen/codegen/codegen.py
sqlmodelgen/codegen/convert_data_type.py
sqlmodelgen/codegen/cir_to_full_ast/code_ir_to_ast.py
sqlmodelgen/codegen/cir_to_full_ast/to_ast_imports.py
sqlmodelgen/codegen/code_ir/build_cir.py
sqlmodelgen/codegen/code_ir/build_col_attrs.py
sqlmodelgen/codegen/code_ir/build_common.py
sqlmodelgen/codegen/code_ir/build_rels.py
sqlmodelgen/codegen/code_ir/build_table_args.py
sqlmodelgen/codegen/code_ir/code_ir.py
sqlmodelgen/ir/ir.py
sqlmodelgen/ir/mysql/__init__.py
sqlmodelgen/ir/parse/ir_parse.py
sqlmodelgen/ir/parse/org_parse.py
sqlmodelgen/ir/postgres/postgres_collect.py
sqlmodelgen/ir/query/__init__.py
sqlmodelgen/ir/sqlite/sqlite_parse.py
sqlmodelgen/utils/dependency_checker.py
sqlmodelgen-0.0.16.dist-info/METADATA
sqlmodelgen-0.0.16.dist-info/WHEEL
sqlmodelgen-0.0.16.dist-info/licenses/LICENSE
sqlmodelgen-0.0.16.dist-info/RECORD
