Metadata-Version: 2.4
Name: sqlmodelgen
Version: 0.0.16
Summary: Generate SQLModel code from SQL
License: MIT License
License-File: LICENSE
Classifier: Development Status :: 3 - Alpha
Classifier: Intended Audience :: Developers
Classifier: License :: OSI Approved :: MIT License
Classifier: Programming Language :: Python :: 3.10
Classifier: Programming Language :: Python :: 3.11
Classifier: Programming Language :: Python :: 3.12
Classifier: Programming Language :: Python :: 3.13
Classifier: Programming Language :: Python :: 3.14
Classifier: Topic :: Database
Classifier: Topic :: Software Development :: Code Generators
Requires-Python: >=3.10
Requires-Dist: sqloxide>=0.1.56
Provides-Extra: mysql
Requires-Dist: mysql-connector-python>=9.5.0; extra == 'mysql'
Provides-Extra: postgres
Requires-Dist: psycopg[binary]>=3.2.6; extra == 'postgres'
